[{"date": "2020-02-27", "diedCumulativeNew": 0}, {"date": "2020-02-28", "diedCumulativeNew": 0}, {"date": "2020-02-29", "diedCumulativeNew": 0}, {"date": "2020-03-01", "diedCumulativeNew": 0}, {"date": "2020-03-02", "diedCumulativeNew": 0}, {"date": "2020-03-03", "diedCumulativeNew": 0}, {"date": "2020-03-04", "diedCumulativeNew": 0}, {"date": "2020-03-05", "diedCumulativeNew": 0}, {"date": "2020-03-06", "diedCumulativeNew": 0}, {"date": "2020-03-07", "diedCumulativeNew": 0}, {"date": "2020-03-08", "diedCumulativeNew": 2}, {"date": "2020-03-09", "diedCumulativeNew": 2}, {"date": "2020-03-10", "diedCumulativeNew": 2}, {"date": "2020-03-11", "diedCumulativeNew": 3}, {"date": "2020-03-12", "diedCumulativeNew": 4}, {"date": "2020-03-13", "diedCumulativeNew": 4}, {"date": "2020-03-14", "diedCumulativeNew": 5}, {"date": "2020-03-15", "diedCumulativeNew": 8}, {"date": "2020-03-16", "diedCumulativeNew": 13}, {"date": "2020-03-17", "diedCumulativeNew": 15}, {"date": "2020-03-18", "diedCumulativeNew": 20}, {"date": "2020-03-19", "diedCumulativeNew": 27}, {"date": "2020-03-20", "diedCumulativeNew": 32}, {"date": "2020-03-21", "diedCumulativeNew": 44}, {"date": "2020-03-22", "diedCumulativeNew": 50}, {"date": "2020-03-23", "diedCumulativeNew": 67}, {"date": "2020-03-24", "diedCumulativeNew": 74}, {"date": "2020-03-25", "diedCumulativeNew": 86}, {"date": "2020-03-26", "diedCumulativeNew": 108}, {"date": "2020-03-27", "diedCumulativeNew": 122}, {"date": "2020-03-28", "diedCumulativeNew": 139}, {"date": "2020-03-29", "diedCumulativeNew": 165}, {"date": "2020-03-30", "diedCumulativeNew": 184}, {"date": "2020-03-31", "diedCumulativeNew": 216}, {"date": "2020-04-01", "diedCumulativeNew": 236}, {"date": "2020-04-02", "diedCumulativeNew": 259}, {"date": "2020-04-03", "diedCumulativeNew": 292}, {"date": "2020-04-04", "diedCumulativeNew": 311}, {"date": "2020-04-05", "diedCumulativeNew": 333}, {"date": "2020-04-06", "diedCumulativeNew": 351}, {"date": "2020-04-07", "diedCumulativeNew": 382}, {"date": "2020-04-08", "diedCumulativeNew": 398}, {"date": "2020-04-09", "diedCumulativeNew": 409}, {"date": "2020-04-10", "diedCumulativeNew": 438}, {"date": "2020-04-11", "diedCumulativeNew": 453}, {"date": "2020-04-12", "diedCumulativeNew": 466}, {"date": "2020-04-13", "diedCumulativeNew": 488}, {"date": "2020-04-14", "diedCumulativeNew": 498}, {"date": "2020-04-15", "diedCumulativeNew": 516}, {"date": "2020-04-16", "diedCumulativeNew": 534}, {"date": "2020-04-17", "diedCumulativeNew": 553}, {"date": "2020-04-18", "diedCumulativeNew": 565}, {"date": "2020-04-19", "diedCumulativeNew": 581}, {"date": "2020-04-20", "diedCumulativeNew": 600}, {"date": "2020-04-21", "diedCumulativeNew": 620}, {"date": "2020-04-22", "diedCumulativeNew": 637}, {"date": "2020-04-23", "diedCumulativeNew": 650}, {"date": "2020-04-24", "diedCumulativeNew": 662}, {"date": "2020-04-25", "diedCumulativeNew": 673}, {"date": "2020-04-26", "diedCumulativeNew": 686}, {"date": "2020-04-27", "diedCumulativeNew": 699}, {"date": "2020-04-28", "diedCumulativeNew": 703}, {"date": "2020-04-29", "diedCumulativeNew": 709}, {"date": "2020-04-30", "diedCumulativeNew": 720}, {"date": "2020-05-01", "diedCumulativeNew": 724}, {"date": "2020-05-02", "diedCumulativeNew": 733}, {"date": "2020-05-03", "diedCumulativeNew": 738}, {"date": "2020-05-04", "diedCumulativeNew": 744}, {"date": "2020-05-05", "diedCumulativeNew": 750}, {"date": "2020-05-06", "diedCumulativeNew": 755}, {"date": "2020-05-07", "diedCumulativeNew": 763}, {"date": "2020-05-08", "diedCumulativeNew": 769}, {"date": "2020-05-09", "diedCumulativeNew": 775}, {"date": "2020-05-10", "diedCumulativeNew": 777}, {"date": "2020-05-11", "diedCumulativeNew": 784}, {"date": "2020-05-12", "diedCumulativeNew": 786}, {"date": "2020-05-13", "diedCumulativeNew": 790}, {"date": "2020-05-14", "diedCumulativeNew": 793}, {"date": "2020-05-15", "diedCumulativeNew": 800}, {"date": "2020-05-16", "diedCumulativeNew": 801}, {"date": "2020-05-17", "diedCumulativeNew": 801}, {"date": "2020-05-18", "diedCumulativeNew": 802}, {"date": "2020-05-19", "diedCumulativeNew": 804}, {"date": "2020-05-20", "diedCumulativeNew": 809}, {"date": "2020-05-21", "diedCumulativeNew": 813}, {"date": "2020-05-22", "diedCumulativeNew": 816}, {"date": "2020-05-23", "diedCumulativeNew": 816}, {"date": "2020-05-24", "diedCumulativeNew": 817}, {"date": "2020-05-25", "diedCumulativeNew": 818}, {"date": "2020-05-26", "diedCumulativeNew": 818}]