{
    "data": [
        {
            "date": "2020-02-27",
            "value": 14
        },
        {
            "date": "2020-02-28",
            "value": 15
        },
        {
            "date": "2020-02-29",
            "value": 16
        },
        {
            "date": "2020-03-01",
            "value": 18
        },
        {
            "date": "2020-03-02",
            "value": 18
        },
        {
            "date": "2020-03-03",
            "value": 20
        },
        {
            "date": "2020-03-04",
            "value": 23
        },
        {
            "date": "2020-03-05",
            "value": 25
        },
        {
            "date": "2020-03-06",
            "value": 29
        },
        {
            "date": "2020-03-07",
            "value": 32
        },
        {
            "date": "2020-03-08",
            "value": 38
        },
        {
            "date": "2020-03-09",
            "value": 46
        },
        {
            "date": "2020-03-10",
            "value": 56
        },
        {
            "date": "2020-03-11",
            "value": 66
        },
        {
            "date": "2020-03-12",
            "value": 89
        },
        {
            "date": "2020-03-13",
            "value": 103
        },
        {
            "date": "2020-03-14",
            "value": 123
        },
        {
            "date": "2020-03-15",
            "value": 151
        },
        {
            "date": "2020-03-16",
            "value": 185
        },
        {
            "date": "2020-03-17",
            "value": 222
        },
        {
            "date": "2020-03-18",
            "value": 277
        },
        {
            "date": "2020-03-19",
            "value": 343
        },
        {
            "date": "2020-03-20",
            "value": 430
        },
        {
            "date": "2020-03-21",
            "value": 512
        },
        {
            "date": "2020-03-22",
            "value": 586
        },
        {
            "date": "2020-03-23",
            "value": 689
        },
        {
            "date": "2020-03-24",
            "value": 803
        },
        {
            "date": "2020-03-25",
            "value": 922
        },
        {
            "date": "2020-03-26",
            "value": 1035
        },
        {
            "date": "2020-03-27",
            "value": 1155
        },
        {
            "date": "2020-03-28",
            "value": 1259
        },
        {
            "date": "2020-03-29",
            "value": 1351
        },
        {
            "date": "2020-03-30",
            "value": 1483
        },
        {
            "date": "2020-03-31",
            "value": 1596
        },
        {
            "date": "2020-04-01",
            "value": 1670
        },
        {
            "date": "2020-04-02",
            "value": 1769
        },
        {
            "date": "2020-04-03",
            "value": 1848
        },
        {
            "date": "2020-04-04",
            "value": 1914
        },
        {
            "date": "2020-04-05",
            "value": 1993
        },
        {
            "date": "2020-04-06",
            "value": 2056
        },
        {
            "date": "2020-04-07",
            "value": 2116
        },
        {
            "date": "2020-04-08",
            "value": 2175
        },
        {
            "date": "2020-04-09",
            "value": 2226
        },
        {
            "date": "2020-04-10",
            "value": 2277
        },
        {
            "date": "2020-04-11",
            "value": 2306
        },
        {
            "date": "2020-04-12",
            "value": 2342
        },
        {
            "date": "2020-04-13",
            "value": 2387
        },
        {
            "date": "2020-04-14",
            "value": 2424
        },
        {
            "date": "2020-04-15",
            "value": 2449
        },
        {
            "date": "2020-04-16",
            "value": 2479
        },
        {
            "date": "2020-04-17",
            "value": 2505
        },
        {
            "date": "2020-04-18",
            "value": 2524
        },
        {
            "date": "2020-04-19",
            "value": 2544
        },
        {
            "date": "2020-04-20",
            "value": 2571
        },
        {
            "date": "2020-04-21",
            "value": 2594
        },
        {
            "date": "2020-04-22",
            "value": 2609
        },
        {
            "date": "2020-04-23",
            "value": 2625
        },
        {
            "date": "2020-04-24",
            "value": 2644
        },
        {
            "date": "2020-04-25",
            "value": 2658
        },
        {
            "date": "2020-04-26",
            "value": 2671
        },
        {
            "date": "2020-04-27",
            "value": 2685
        },
        {
            "date": "2020-04-28",
            "value": 2701
        },
        {
            "date": "2020-04-29",
            "value": 2713
        },
        {
            "date": "2020-04-30",
            "value": 2732
        },
        {
            "date": "2020-05-01",
            "value": 2741
        },
        {
            "date": "2020-05-02",
            "value": 2752
        },
        {
            "date": "2020-05-03",
            "value": 2763
        },
        {
            "date": "2020-05-04",
            "value": 2775
        },
        {
            "date": "2020-05-05",
            "value": 2778
        },
        {
            "date": "2020-05-06",
            "value": 2784
        },
        {
            "date": "2020-05-07",
            "value": 2794
        },
        {
            "date": "2020-05-08",
            "value": 2802
        },
        {
            "date": "2020-05-09",
            "value": 2807
        },
        {
            "date": "2020-05-10",
            "value": 2812
        },
        {
            "date": "2020-05-11",
            "value": 2820
        },
        {
            "date": "2020-05-12",
            "value": 2822
        },
        {
            "date": "2020-05-13",
            "value": 2826
        },
        {
            "date": "2020-05-14",
            "value": 2835
        },
        {
            "date": "2020-05-15",
            "value": 2840
        },
        {
            "date": "2020-05-16",
            "value": 2848
        },
        {
            "date": "2020-05-17",
            "value": 2852
        },
        {
            "date": "2020-05-18",
            "value": 2856
        },
        {
            "date": "2020-05-19",
            "value": 2858
        },
        {
            "date": "2020-05-20",
            "value": 2861
        },
        {
            "date": "2020-05-21",
            "value": 2863
        },
        {
            "date": "2020-05-22",
            "value": 2868
        },
        {
            "date": "2020-05-23",
            "value": 2871
        },
        {
            "date": "2020-05-24",
            "value": 2878
        },
        {
            "date": "2020-05-25",
            "value": 2879
        },
        {
            "date": "2020-05-26",
            "value": 2883
        },
        {
            "date": "2020-05-27",
            "value": 2887
        },
        {
            "date": "2020-05-28",
            "value": 2888
        },
        {
            "date": "2020-05-29",
            "value": 2891
        },
        {
            "date": "2020-05-30",
            "value": 2894
        },
        {
            "date": "2020-05-31",
            "value": 2897
        },
        {
            "date": "2020-06-01",
            "value": 2902
        },
        {
            "date": "2020-06-02",
            "value": 2903
        },
        {
            "date": "2020-06-03",
            "value": 2908
        },
        {
            "date": "2020-06-04",
            "value": 2914
        },
        {
            "date": "2020-06-05",
            "value": 2917
        },
        {
            "date": "2020-06-06",
            "value": 2919
        },
        {
            "date": "2020-06-07",
            "value": 2922
        },
        {
            "date": "2020-06-08",
            "value": 2923
        },
        {
            "date": "2020-06-09",
            "value": 2925
        },
        {
            "date": "2020-06-10",
            "value": 2927
        },
        {
            "date": "2020-06-11",
            "value": 2928
        },
        {
            "date": "2020-06-12",
            "value": 2931
        },
        {
            "date": "2020-06-13",
            "value": 2933
        },
        {
            "date": "2020-06-14",
            "value": 2933
        },
        {
            "date": "2020-06-15",
            "value": 2934
        },
        {
            "date": "2020-06-16",
            "value": 2936
        },
        {
            "date": "2020-06-17",
            "value": 2936
        },
        {
            "date": "2020-06-18",
            "value": 2937
        },
        {
            "date": "2020-06-19",
            "value": 2938
        },
        {
            "date": "2020-06-20",
            "value": 2940
        },
        {
            "date": "2020-06-21",
            "value": 2940
        },
        {
            "date": "2020-06-22",
            "value": 2943
        },
        {
            "date": "2020-06-23",
            "value": 2944
        },
        {
            "date": "2020-06-24",
            "value": 2945
        },
        {
            "date": "2020-06-25",
            "value": 2946
        },
        {
            "date": "2020-06-26",
            "value": 2946
        },
        {
            "date": "2020-06-27",
            "value": 2946
        },
        {
            "date": "2020-06-28",
            "value": 2946
        },
        {
            "date": "2020-06-29",
            "value": 2946
        },
        {
            "date": "2020-06-30",
            "value": 2948
        },
        {
            "date": "2020-07-01",
            "value": 2948
        },
        {
            "date": "2020-07-02",
            "value": 2951
        },
        {
            "date": "2020-07-03",
            "value": 2951
        },
        {
            "date": "2020-07-04",
            "value": 2952
        },
        {
            "date": "2020-07-05",
            "value": 2952
        },
        {
            "date": "2020-07-06",
            "value": 2953
        },
        {
            "date": "2020-07-07",
            "value": 2954
        },
        {
            "date": "2020-07-08",
            "value": 2956
        },
        {
            "date": "2020-07-09",
            "value": 2957
        },
        {
            "date": "2020-07-10",
            "value": 2958
        },
        {
            "date": "2020-07-11",
            "value": 2958
        },
        {
            "date": "2020-07-12",
            "value": 2959
        },
        {
            "date": "2020-07-13",
            "value": 2959
        },
        {
            "date": "2020-07-14",
            "value": 2959
        },
        {
            "date": "2020-07-15",
            "value": 2960
        },
        {
            "date": "2020-07-16",
            "value": 2961
        },
        {
            "date": "2020-07-17",
            "value": 2961
        },
        {
            "date": "2020-07-18",
            "value": 2961
        },
        {
            "date": "2020-07-19",
            "value": 2962
        },
        {
            "date": "2020-07-20",
            "value": 2963
        },
        {
            "date": "2020-07-21",
            "value": 2965
        },
        {
            "date": "2020-07-22",
            "value": 2966
        },
        {
            "date": "2020-07-23",
            "value": 2967
        },
        {
            "date": "2020-07-24",
            "value": 2969
        },
        {
            "date": "2020-07-25",
            "value": 2970
        },
        {
            "date": "2020-07-26",
            "value": 2972
        },
        {
            "date": "2020-07-27",
            "value": 2976
        },
        {
            "date": "2020-07-28",
            "value": 2976
        },
        {
            "date": "2020-07-29",
            "value": 2976
        },
        {
            "date": "2020-07-30",
            "value": 2979
        },
        {
            "date": "2020-07-31",
            "value": 2983
        },
        {
            "date": "2020-08-01",
            "value": 2985
        },
        {
            "date": "2020-08-02",
            "value": 2987
        },
        {
            "date": "2020-08-03",
            "value": 2990
        },
        {
            "date": "2020-08-04",
            "value": 2993
        },
        {
            "date": "2020-08-05",
            "value": 2995
        },
        {
            "date": "2020-08-06",
            "value": 2997
        },
        {
            "date": "2020-08-07",
            "value": 2998
        },
        {
            "date": "2020-08-08",
            "value": 2999
        },
        {
            "date": "2020-08-09",
            "value": 3005
        },
        {
            "date": "2020-08-10",
            "value": 3009
        },
        {
            "date": "2020-08-11",
            "value": 3012
        },
        {
            "date": "2020-08-12",
            "value": 3016
        },
        {
            "date": "2020-08-13",
            "value": 3020
        },
        {
            "date": "2020-08-14",
            "value": 3026
        },
        {
            "date": "2020-08-15",
            "value": 3027
        },
        {
            "date": "2020-08-16",
            "value": 3031
        },
        {
            "date": "2020-08-17",
            "value": 3040
        },
        {
            "date": "2020-08-18",
            "value": 3042
        },
        {
            "date": "2020-08-19",
            "value": 3045
        },
        {
            "date": "2020-08-20",
            "value": 3050
        },
        {
            "date": "2020-08-21",
            "value": 3056
        },
        {
            "date": "2020-08-22",
            "value": 3056
        },
        {
            "date": "2020-08-23",
            "value": 3061
        },
        {
            "date": "2020-08-24",
            "value": 3063
        },
        {
            "date": "2020-08-25",
            "value": 3066
        },
        {
            "date": "2020-08-26",
            "value": 3066
        },
        {
            "date": "2020-08-27",
            "value": 3069
        },
        {
            "date": "2020-08-28",
            "value": 3071
        },
        {
            "date": "2020-08-29",
            "value": 3074
        },
        {
            "date": "2020-08-30",
            "value": 3077
        },
        {
            "date": "2020-08-31",
            "value": 3078
        },
        {
            "date": "2020-09-01",
            "value": 3080
        },
        {
            "date": "2020-09-02",
            "value": 3081
        },
        {
            "date": "2020-09-03",
            "value": 3085
        },
        {
            "date": "2020-09-04",
            "value": 3089
        },
        {
            "date": "2020-09-05",
            "value": 3090
        },
        {
            "date": "2020-09-06",
            "value": 3094
        },
        {
            "date": "2020-09-07",
            "value": 3097
        },
        {
            "date": "2020-09-08",
            "value": 3101
        },
        {
            "date": "2020-09-09",
            "value": 3104
        },
        {
            "date": "2020-09-10",
            "value": 3109
        },
        {
            "date": "2020-09-11",
            "value": 3115
        },
        {
            "date": "2020-09-12",
            "value": 3121
        },
        {
            "date": "2020-09-13",
            "value": 3125
        },
        {
            "date": "2020-09-14",
            "value": 3135
        },
        {
            "date": "2020-09-15",
            "value": 3140
        },
        {
            "date": "2020-09-16",
            "value": 3141
        },
        {
            "date": "2020-09-17",
            "value": 3145
        },
        {
            "date": "2020-09-18",
            "value": 3152
        },
        {
            "date": "2020-09-19",
            "value": 3165
        },
        {
            "date": "2020-09-20",
            "value": 3180
        },
        {
            "date": "2020-09-21",
            "value": 3193
        },
        {
            "date": "2020-09-22",
            "value": 3204
        },
        {
            "date": "2020-09-23",
            "value": 3216
        },
        {
            "date": "2020-09-24",
            "value": 3227
        },
        {
            "date": "2020-09-25",
            "value": 3245
        },
        {
            "date": "2020-09-26",
            "value": 3258
        },
        {
            "date": "2020-09-27",
            "value": 3277
        },
        {
            "date": "2020-09-28",
            "value": 3292
        },
        {
            "date": "2020-09-29",
            "value": 3315
        },
        {
            "date": "2020-09-30",
            "value": 3332
        },
        {
            "date": "2020-10-01",
            "value": 3345
        },
        {
            "date": "2020-10-02",
            "value": 3359
        },
        {
            "date": "2020-10-03",
            "value": 3378
        },
        {
            "date": "2020-10-04",
            "value": 3400
        },
        {
            "date": "2020-10-05",
            "value": 3428
        },
        {
            "date": "2020-10-06",
            "value": 3461
        },
        {
            "date": "2020-10-07",
            "value": 3491
        },
        {
            "date": "2020-10-08",
            "value": 3514
        },
        {
            "date": "2020-10-09",
            "value": 3541
        },
        {
            "date": "2020-10-10",
            "value": 3568
        },
        {
            "date": "2020-10-11",
            "value": 3587
        },
        {
            "date": "2020-10-12",
            "value": 3629
        },
        {
            "date": "2020-10-13",
            "value": 3666
        },
        {
            "date": "2020-10-14",
            "value": 3701
        },
        {
            "date": "2020-10-15",
            "value": 3740
        },
        {
            "date": "2020-10-16",
            "value": 3796
        },
        {
            "date": "2020-10-17",
            "value": 3828
        },
        {
            "date": "2020-10-18",
            "value": 3868
        },
        {
            "date": "2020-10-19",
            "value": 3928
        },
        {
            "date": "2020-10-20",
            "value": 3979
        },
        {
            "date": "2020-10-21",
            "value": 4029
        },
        {
            "date": "2020-10-22",
            "value": 4072
        },
        {
            "date": "2020-10-23",
            "value": 4123
        },
        {
            "date": "2020-10-24",
            "value": 4164
        },
        {
            "date": "2020-10-25",
            "value": 4212
        },
        {
            "date": "2020-10-26",
            "value": 4270
        },
        {
            "date": "2020-10-27",
            "value": 4322
        },
        {
            "date": "2020-10-28",
            "value": 4376
        },
        {
            "date": "2020-10-29",
            "value": 4422
        },
        {
            "date": "2020-10-30",
            "value": 4465
        },
        {
            "date": "2020-10-31",
            "value": 4514
        },
        {
            "date": "2020-11-01",
            "value": 4557
        },
        {
            "date": "2020-11-02",
            "value": 4618
        },
        {
            "date": "2020-11-03",
            "value": 4653
        },
        {
            "date": "2020-11-04",
            "value": 4693
        },
        {
            "date": "2020-11-05",
            "value": 4730
        },
        {
            "date": "2020-11-06",
            "value": 4765
        },
        {
            "date": "2020-11-07",
            "value": 4804
        },
        {
            "date": "2020-11-08",
            "value": 4848
        },
        {
            "date": "2020-11-09",
            "value": 4890
        },
        {
            "date": "2020-11-10",
            "value": 4929
        },
        {
            "date": "2020-11-11",
            "value": 4965
        },
        {
            "date": "2020-11-12",
            "value": 5006
        },
        {
            "date": "2020-11-13",
            "value": 5037
        },
        {
            "date": "2020-11-14",
            "value": 5060
        },
        {
            "date": "2020-11-15",
            "value": 5094
        },
        {
            "date": "2020-11-16",
            "value": 5130
        },
        {
            "date": "2020-11-17",
            "value": 5160
        },
        {
            "date": "2020-11-18",
            "value": 5192
        },
        {
            "date": "2020-11-19",
            "value": 5231
        },
        {
            "date": "2020-11-20",
            "value": 5262
        },
        {
            "date": "2020-11-21",
            "value": 5282
        },
        {
            "date": "2020-11-22",
            "value": 5308
        },
        {
            "date": "2020-11-23",
            "value": 5333
        },
        {
            "date": "2020-11-24",
            "value": 5369
        },
        {
            "date": "2020-11-25",
            "value": 5408
        },
        {
            "date": "2020-11-26",
            "value": 5438
        },
        {
            "date": "2020-11-27",
            "value": 5455
        },
        {
            "date": "2020-11-28",
            "value": 5477
        },
        {
            "date": "2020-11-29",
            "value": 5496
        },
        {
            "date": "2020-11-30",
            "value": 5522
        },
        {
            "date": "2020-12-01",
            "value": 5554
        },
        {
            "date": "2020-12-02",
            "value": 5583
        },
        {
            "date": "2020-12-03",
            "value": 5615
        },
        {
            "date": "2020-12-04",
            "value": 5648
        },
        {
            "date": "2020-12-05",
            "value": 5674
        },
        {
            "date": "2020-12-06",
            "value": 5702
        },
        {
            "date": "2020-12-07",
            "value": 5723
        },
        {
            "date": "2020-12-08",
            "value": 5763
        },
        {
            "date": "2020-12-09",
            "value": 5797
        },
        {
            "date": "2020-12-10",
            "value": 5832
        },
        {
            "date": "2020-12-11",
            "value": 5868
        },
        {
            "date": "2020-12-12",
            "value": 5890
        },
        {
            "date": "2020-12-13",
            "value": 5934
        },
        {
            "date": "2020-12-14",
            "value": 5959
        },
        {
            "date": "2020-12-15",
            "value": 6005
        },
        {
            "date": "2020-12-16",
            "value": 6042
        },
        {
            "date": "2020-12-17",
            "value": 6091
        },
        {
            "date": "2020-12-18",
            "value": 6129
        },
        {
            "date": "2020-12-19",
            "value": 6175
        },
        {
            "date": "2020-12-20",
            "value": 6230
        },
        {
            "date": "2020-12-21",
            "value": 6264
        },
        {
            "date": "2020-12-22",
            "value": 6307
        },
        {
            "date": "2020-12-23",
            "value": 6357
        },
        {
            "date": "2020-12-24",
            "value": 6405
        },
        {
            "date": "2020-12-25",
            "value": 6445
        },
        {
            "date": "2020-12-26",
            "value": 6489
        },
        {
            "date": "2020-12-27",
            "value": 6533
        },
        {
            "date": "2020-12-28",
            "value": 6603
        },
        {
            "date": "2020-12-29",
            "value": 6663
        },
        {
            "date": "2020-12-30",
            "value": 6711
        },
        {
            "date": "2020-12-31",
            "value": 6751
        },
        {
            "date": "2021-01-01",
            "value": 6792
        },
        {
            "date": "2021-01-02",
            "value": 6832
        },
        {
            "date": "2021-01-03",
            "value": 6877
        },
        {
            "date": "2021-01-04",
            "value": 6935
        },
        {
            "date": "2021-01-05",
            "value": 6989
        },
        {
            "date": "2021-01-06",
            "value": 7035
        },
        {
            "date": "2021-01-07",
            "value": 7072
        },
        {
            "date": "2021-01-08",
            "value": 7113
        },
        {
            "date": "2021-01-09",
            "value": 7144
        },
        {
            "date": "2021-01-10",
            "value": 7177
        },
        {
            "date": "2021-01-11",
            "value": 7216
        },
        {
            "date": "2021-01-12",
            "value": 7260
        },
        {
            "date": "2021-01-13",
            "value": 7299
        },
        {
            "date": "2021-01-14",
            "value": 7333
        },
        {
            "date": "2021-01-15",
            "value": 7368
        },
        {
            "date": "2021-01-16",
            "value": 7393
        },
        {
            "date": "2021-01-17",
            "value": 7430
        },
        {
            "date": "2021-01-18",
            "value": 7468
        },
        {
            "date": "2021-01-19",
            "value": 7497
        },
        {
            "date": "2021-01-20",
            "value": 7505
        }
    ],
    "license": "\n    vermeld dat het artikel van www.stichting-nice.nl komt,\n    vermeld dat het artikel copyright 1996-2020 van Stichting NICE is,\n    vermeld een duidelijke en werkende link naar de juiste pagina op de website van Stichting NICE.\n",
    "source": "https://www.stichting-nice.nl/covid-19/public/intake-cumulative/"
}