[{"date":"2020-02-27","value":6},{"date":"2020-02-28","value":7},{"date":"2020-02-29","value":8},{"date":"2020-03-01","value":10},{"date":"2020-03-02","value":9},{"date":"2020-03-03","value":10},{"date":"2020-03-04","value":13},{"date":"2020-03-05","value":14},{"date":"2020-03-06","value":17},{"date":"2020-03-07","value":19},{"date":"2020-03-08","value":25},{"date":"2020-03-09","value":29},{"date":"2020-03-10","value":35},{"date":"2020-03-11","value":45},{"date":"2020-03-12","value":67},{"date":"2020-03-13","value":78},{"date":"2020-03-14","value":94},{"date":"2020-03-15","value":118},{"date":"2020-03-16","value":146},{"date":"2020-03-17","value":174},{"date":"2020-03-18","value":224},{"date":"2020-03-19","value":283},{"date":"2020-03-20","value":357},{"date":"2020-03-21","value":427},{"date":"2020-03-22","value":481},{"date":"2020-03-23","value":573},{"date":"2020-03-24","value":653},{"date":"2020-03-25","value":753},{"date":"2020-03-26","value":836},{"date":"2020-03-27","value":923},{"date":"2020-03-28","value":989},{"date":"2020-03-29","value":1037},{"date":"2020-03-30","value":1126},{"date":"2020-03-31","value":1190},{"date":"2020-04-01","value":1207},{"date":"2020-04-02","value":1250},{"date":"2020-04-03","value":1280},{"date":"2020-04-04","value":1282},{"date":"2020-04-05","value":1303},{"date":"2020-04-06","value":1311},{"date":"2020-04-07","value":1314},{"date":"2020-04-08","value":1287},{"date":"2020-04-09","value":1282},{"date":"2020-04-10","value":1286},{"date":"2020-04-11","value":1253},{"date":"2020-04-12","value":1234},{"date":"2020-04-13","value":1221},{"date":"2020-04-14","value":1194},{"date":"2020-04-15","value":1170},{"date":"2020-04-16","value":1138},{"date":"2020-04-17","value":1108},{"date":"2020-04-18","value":1061},{"date":"2020-04-19","value":1031},{"date":"2020-04-20","value":1011},{"date":"2020-04-21","value":975},{"date":"2020-04-22","value":919},{"date":"2020-04-23","value":879},{"date":"2020-04-24","value":861},{"date":"2020-04-25","value":832},{"date":"2020-04-26","value":808},{"date":"2020-04-27","value":786},{"date":"2020-04-28","value":763},{"date":"2020-04-29","value":734},{"date":"2020-04-30","value":710},{"date":"2020-05-01","value":675},{"date":"2020-05-02","value":634},{"date":"2020-05-03","value":622},{"date":"2020-05-04","value":612},{"date":"2020-05-05","value":570},{"date":"2020-05-06","value":544},{"date":"2020-05-07","value":523},{"date":"2020-05-08","value":492},{"date":"2020-05-09","value":469},{"date":"2020-05-10","value":452},{"date":"2020-05-11","value":446},{"date":"2020-05-12","value":405},{"date":"2020-05-13","value":386},{"date":"2020-05-14","value":364},{"date":"2020-05-15","value":349},{"date":"2020-05-16","value":333},{"date":"2020-05-17","value":327},{"date":"2020-05-18","value":320},{"date":"2020-05-19","value":289},{"date":"2020-05-20","value":278},{"date":"2020-05-21","value":258},{"date":"2020-05-22","value":245},{"date":"2020-05-23","value":230},{"date":"2020-05-24","value":229},{"date":"2020-05-25","value":219},{"date":"2020-05-26","value":199},{"date":"2020-05-27","value":192},{"date":"2020-05-28","value":188}]