[{"date": "2020-02-21", "newIntake": 1, "diedCumulative": 0, "intakeCount": 0, "intakeCumulative": 0, "icCount": 0, "icCumulative": 0}, {"date": "2020-02-25", "newIntake": 1, "diedCumulative": 0, "intakeCount": 0, "intakeCumulative": 0, "icCount": 0, "icCumulative": 0}, {"date": "2020-03-01", "newIntake": 1, "diedCumulative": 0, "intakeCount": 0, "intakeCumulative": 0, "icCount": 0, "icCumulative": 0}, {"date": "2020-03-03", "newIntake": 1, "diedCumulative": 0, "intakeCount": 0, "intakeCumulative": 0, "icCount": 0, "icCumulative": 0}, {"date": "2020-03-04", "newIntake": 3, "diedCumulative": 0, "intakeCount": 0, "intakeCumulative": 0, "icCount": 0, "icCumulative": 0}, {"date": "2020-03-05", "newIntake": 1, "diedCumulative": 0, "intakeCount": 0, "intakeCumulative": 0, "icCount": 0, "icCumulative": 0}, {"date": "2020-03-06", "newIntake": 3, "diedCumulative": 0, "intakeCount": 0, "intakeCumulative": 0, "icCount": 0, "icCumulative": 0}, {"date": "2020-03-07", "newIntake": 3, "diedCumulative": 0, "intakeCount": 0, "intakeCumulative": 0, "icCount": 0, "icCumulative": 0}, {"date": "2020-03-08", "newIntake": 5, "diedCumulative": 0, "intakeCount": 0, "intakeCumulative": 0, "icCount": 0, "icCumulative": 0}, {"date": "2020-03-09", "newIntake": 5, "diedCumulative": 0, "intakeCount": 0, "intakeCumulative": 0, "icCount": 0, "icCumulative": 0}, {"date": "2020-03-10", "newIntake": 8, "diedCumulative": 0, "intakeCount": 0, "intakeCumulative": 0, "icCount": 0, "icCumulative": 0}, {"date": "2020-03-11", "newIntake": 6, "diedCumulative": 0, "intakeCount": 0, "intakeCumulative": 0, "icCount": 0, "icCumulative": 0}, {"date": "2020-03-12", "newIntake": 22, "diedCumulative": 0, "intakeCount": 0, "intakeCumulative": 0, "icCount": 0, "icCumulative": 0}, {"date": "2020-03-13", "newIntake": 14, "diedCumulative": 0, "intakeCount": 0, "intakeCumulative": 0, "icCount": 0, "icCumulative": 0}, {"date": "2020-03-14", "newIntake": 17, "diedCumulative": 0, "intakeCount": 0, "intakeCumulative": 0, "icCount": 0, "icCumulative": 0}, {"date": "2020-03-15", "newIntake": 27, "diedCumulative": 0, "intakeCount": 0, "intakeCumulative": 0, "icCount": 0, "icCumulative": 0}, {"date": "2020-03-16", "newIntake": 32, "diedCumulative": 0, "intakeCount": 0, "intakeCumulative": 0, "icCount": 0, "icCumulative": 0}, {"date": "2020-03-17", "newIntake": 35, "diedCumulative": 0, "intakeCount": 0, "intakeCumulative": 0, "icCount": 0, "icCumulative": 0}, {"date": "2020-03-18", "newIntake": 51, "diedCumulative": 0, "intakeCount": 0, "intakeCumulative": 0, "icCount": 0, "icCumulative": 0}, {"date": "2020-03-19", "newIntake": 59, "diedCumulative": 0, "intakeCount": 0, "intakeCumulative": 0, "icCount": 0, "icCumulative": 0}, {"date": "2020-03-20", "newIntake": 86, "diedCumulative": 0, "intakeCount": 0, "intakeCumulative": 0, "icCount": 0, "icCumulative": 0}, {"date": "2020-03-21", "newIntake": 71, "diedCumulative": 0, "intakeCount": 0, "intakeCumulative": 0, "icCount": 0, "icCumulative": 0}, {"date": "2020-03-22", "newIntake": 71, "diedCumulative": 0, "intakeCount": 0, "intakeCumulative": 0, "icCount": 0, "icCumulative": 0}, {"date": "2020-03-23", "newIntake": 102, "diedCumulative": 0, "intakeCount": 0, "intakeCumulative": 0, "icCount": 0, "icCumulative": 0}, {"date": "2020-03-24", "newIntake": 108, "diedCumulative": 0, "intakeCount": 0, "intakeCumulative": 0, "icCount": 0, "icCumulative": 0}, {"date": "2020-03-25", "newIntake": 116, "diedCumulative": 0, "intakeCount": 0, "intakeCumulative": 0, "icCount": 0, "icCumulative": 0}, {"date": "2020-03-26", "newIntake": 100, "diedCumulative": 0, "intakeCount": 0, "intakeCumulative": 0, "icCount": 0, "icCumulative": 0}, {"date": "2020-03-27", "newIntake": 115, "diedCumulative": 0, "intakeCount": 0, "intakeCumulative": 0, "icCount": 0, "icCumulative": 0}, {"date": "2020-03-28", "newIntake": 103, "diedCumulative": 0, "intakeCount": 0, "intakeCumulative": 0, "icCount": 0, "icCumulative": 0}, {"date": "2020-03-29", "newIntake": 95, "diedCumulative": 0, "intakeCount": 0, "intakeCumulative": 0, "icCount": 0, "icCumulative": 0}, {"date": "2020-03-30", "newIntake": 131, "diedCumulative": 0, "intakeCount": 0, "intakeCumulative": 0, "icCount": 0, "icCumulative": 0}, {"date": "2020-03-31", "newIntake": 105, "diedCumulative": 0, "intakeCount": 0, "intakeCumulative": 0, "icCount": 0, "icCumulative": 0}, {"date": "2020-04-01", "newIntake": 76, "diedCumulative": 0, "intakeCount": 0, "intakeCumulative": 0, "icCount": 0, "icCumulative": 0}, {"date": "2020-04-02", "newIntake": 97, "diedCumulative": 0, "intakeCount": 0, "intakeCumulative": 0, "icCount": 0, "icCumulative": 0}, {"date": "2020-04-03", "newIntake": 82, "diedCumulative": 0, "intakeCount": 0, "intakeCumulative": 0, "icCount": 0, "icCumulative": 0}, {"date": "2020-04-04", "newIntake": 54, "diedCumulative": 0, "intakeCount": 0, "intakeCumulative": 0, "icCount": 0, "icCumulative": 0}, {"date": "2020-04-05", "newIntake": 64, "diedCumulative": 0, "intakeCount": 0, "intakeCumulative": 0, "icCount": 0, "icCumulative": 0}, {"date": "2020-04-06", "newIntake": 18, "diedCumulative": 0, "intakeCount": 0, "intakeCumulative": 0, "icCount": 0, "icCumulative": 0}]