{
  "schema": {
    "fields": [
      {
        "name": "Datum",
        "type": "string"
      },
      {
        "name": "Provincienaam",
        "type": "string"
      },
      {
        "name": "Provinciecode",
        "type": "integer"
      },
      {
        "name": "overledenAantal",
        "type": "integer"
      },
      {
        "name": "totaalAantal",
        "type": "integer"
      },
      {
        "name": "ziekenhuisopnameAantal",
        "type": "integer"
      },
      {
        "name": "overledenAantalCumulatief",
        "type": "integer"
      },
      {
        "name": "totaalAantalCumulatief",
        "type": "integer"
      },
      {
        "name": "ziekenhuisopnameAantalCumulatief",
        "type": "integer"
      }
    ]
  },
  "data": [
    {
      "Datum": "2021-02-16",
      "Provincienaam": "Drenthe",
      "Provinciecode": 22,
      "overledenAantal": 0,
      "totaalAantal": 108,
      "ziekenhuisopnameAantal": 1,
      "overledenAantalCumulatief": 272,
      "totaalAantalCumulatief": 20277,
      "ziekenhuisopnameAantalCumulatief": 353
    },
    {
      "Datum": "2021-02-16",
      "Provincienaam": "Flevoland",
      "Provinciecode": 24,
      "overledenAantal": 1,
      "totaalAantal": 43,
      "ziekenhuisopnameAantal": 1,
      "overledenAantalCumulatief": 201,
      "totaalAantalCumulatief": 24908,
      "ziekenhuisopnameAantalCumulatief": 511
    },
    {
      "Datum": "2021-02-16",
      "Provincienaam": "Friesland",
      "Provinciecode": 21,
      "overledenAantal": 4,
      "totaalAantal": 118,
      "ziekenhuisopnameAantal": 3,
      "overledenAantalCumulatief": 337,
      "totaalAantalCumulatief": 24115,
      "ziekenhuisopnameAantalCumulatief": 335
    },
    {
      "Datum": "2021-02-16",
      "Provincienaam": "Gelderland",
      "Provinciecode": 25,
      "overledenAantal": 11,
      "totaalAantal": 227,
      "ziekenhuisopnameAantal": 4,
      "overledenAantalCumulatief": 1754,
      "totaalAantalCumulatief": 117178,
      "ziekenhuisopnameAantalCumulatief": 2501
    },
    {
      "Datum": "2021-02-16",
      "Provincienaam": "Groningen",
      "Provinciecode": 20,
      "overledenAantal": 1,
      "totaalAantal": 106,
      "ziekenhuisopnameAantal": 4,
      "overledenAantalCumulatief": 163,
      "totaalAantalCumulatief": 20883,
      "ziekenhuisopnameAantalCumulatief": 246
    },
    {
      "Datum": "2021-02-16",
      "Provincienaam": "Limburg",
      "Provinciecode": 31,
      "overledenAantal": 8,
      "totaalAantal": 206,
      "ziekenhuisopnameAantal": 0,
      "overledenAantalCumulatief": 1381,
      "totaalAantalCumulatief": 68102,
      "ziekenhuisopnameAantalCumulatief": 2186
    },
    {
      "Datum": "2021-02-16",
      "Provincienaam": "Noord-Brabant",
      "Provinciecode": 30,
      "overledenAantal": 14,
      "totaalAantal": 415,
      "ziekenhuisopnameAantal": 2,
      "overledenAantalCumulatief": 2789,
      "totaalAantalCumulatief": 161622,
      "ziekenhuisopnameAantalCumulatief": 4192
    },
    {
      "Datum": "2021-02-16",
      "Provincienaam": "Noord-Holland",
      "Provinciecode": 27,
      "overledenAantal": 14,
      "totaalAantal": 595,
      "ziekenhuisopnameAantal": 11,
      "overledenAantalCumulatief": 2151,
      "totaalAantalCumulatief": 175342,
      "ziekenhuisopnameAantalCumulatief": 3599
    },
    {
      "Datum": "2021-02-16",
      "Provincienaam": "Overijssel",
      "Provinciecode": 23,
      "overledenAantal": 8,
      "totaalAantal": 128,
      "ziekenhuisopnameAantal": 8,
      "overledenAantalCumulatief": 1005,
      "totaalAantalCumulatief": 73058,
      "ziekenhuisopnameAantalCumulatief": 1104
    },
    {
      "Datum": "2021-02-16",
      "Provincienaam": "Utrecht",
      "Provinciecode": 26,
      "overledenAantal": 7,
      "totaalAantal": 176,
      "ziekenhuisopnameAantal": 5,
      "overledenAantalCumulatief": 1082,
      "totaalAantalCumulatief": 82711,
      "ziekenhuisopnameAantalCumulatief": 1939
    },
    {
      "Datum": "2021-02-16",
      "Provincienaam": "Zeeland",
      "Provinciecode": 29,
      "overledenAantal": 4,
      "totaalAantal": 37,
      "ziekenhuisopnameAantal": 0,
      "overledenAantalCumulatief": 170,
      "totaalAantalCumulatief": 15452,
      "ziekenhuisopnameAantalCumulatief": 450
    },
    {
      "Datum": "2021-02-16",
      "Provincienaam": "Zuid-Holland",
      "Provinciecode": 28,
      "overledenAantal": 13,
      "totaalAantal": 554,
      "ziekenhuisopnameAantal": 17,
      "overledenAantalCumulatief": 3581,
      "totaalAantalCumulatief": 245693,
      "ziekenhuisopnameAantalCumulatief": 5897
    }
  ],
  "apiVersion": "0.1"
}