{
  "schema": {
    "fields": [
      {
        "name": "Datum",
        "type": "string"
      },
      {
        "name": "overledenAantal",
        "type": "integer"
      },
      {
        "name": "totaalAantal",
        "type": "integer"
      },
      {
        "name": "ziekenhuisopnameAantal",
        "type": "integer"
      },
      {
        "name": "overledenAantalCumulatief",
        "type": "integer"
      },
      {
        "name": "totaalAantalCumulatief",
        "type": "integer"
      },
      {
        "name": "ziekenhuisopnameAantalCumulatief",
        "type": "integer"
      }
    ]
  },
  "data": [
    {
      "Datum": "2021-01-15",
      "overledenAantal": 94,
      "totaalAantal": 6009,
      "ziekenhuisopnameAantal": 76,
      "overledenAantalCumulatief": 12868,
      "totaalAantalCumulatief": 901696,
      "ziekenhuisopnameAantalCumulatief": 21287
    }
  ],
  "apiVersion": "0.1"
}